{
  "name": "Victory Fanfare",
  "tempo": 160,
  "loop": false,
  "tracks": [
    {
      "name": "melody",
      "instrument": {
        "type": "sine",
        "volume": 0.4
      },
      "pattern": {
        "notes": ["C5", "E5", "G5", "C6"],
        "durations": [0.2, 0.2, 0.2, 0.6],
        "times": [0, 0.2, 0.4, 0.6]
      }
    },
    {
      "name": "harmony",
      "instrument": {
        "type": "triangle",
        "volume": 0.3
      },
      "pattern": {
        "chords": [["C4", "E4", "G4", "C5"]],
        "durations": [1.2],
        "times": [0]
      }
    }
  ]
}